LICENSE
MANIFEST.in
README.md
setup.py
nl4dv/__init__.py
nl4dv.egg-info/PKG-INFO
nl4dv.egg-info/SOURCES.txt
nl4dv.egg-info/dependency_links.txt
nl4dv.egg-info/requires.txt
nl4dv.egg-info/top_level.txt
nl4dv/attributegenie/__init__.py
nl4dv/attributegenie/attributegenie.py
nl4dv/autogenie/__init__.py
nl4dv/autogenie/autogenie.py
nl4dv/conversationgenie/__init__.py
nl4dv/conversationgenie/conversationgenie.py
nl4dv/datagenie/__init__.py
nl4dv/datagenie/datagenie.py
nl4dv/lm_designgenie/__init__.py
nl4dv/lm_designgenie/lm_designgenie.py
nl4dv/lm_querygenie/__init__.py
nl4dv/lm_querygenie/lm_querygenie.py
nl4dv/querygenie/__init__.py
nl4dv/querygenie/querygenie.py
nl4dv/taskgenie/__init__.py
nl4dv/taskgenie/taskgenie.py
nl4dv/tests/__init__.py
nl4dv/tests/test_data_summary.py
nl4dv/tests/test_queries.py
nl4dv/updategenie/__init__.py
nl4dv/updategenie/updategenie.py
nl4dv/utils/__init__.py
nl4dv/utils/constants.py
nl4dv/utils/error_codes.py
nl4dv/utils/helpers.py
nl4dv/visgenie/__init__.py
nl4dv/visgenie/vis_recos.py
nl4dv/visgenie/visgenie.py
nl4dv/vlgenie/__init__.py
nl4dv/vlgenie/vlgenie.py