Metadata-Version: 2.4
Name: nl4dv
Version: 4.1.0
Summary: NL4DV is a Python toolkit that takes a natural language (NL) query about a given dataset as input and outputs a structured JSON object containing Data attributes, Analytic tasks, and Visualizations (Vega-Lite specifications).
Home-page: https://github.com/nl4dv/nl4dv
Author: Arpit Narechania
Author-email: arpitnarechania@gmail.com
License: LICENSE
License-File: LICENSE
Requires-Dist: fuzzywuzzy~=0.8.1
Requires-Dist: inflect~=5.5
Requires-Dist: levenshtein~=0.27.1
Requires-Dist: litellm~=1.71.1
Requires-Dist: nltk~=3.5
Requires-Dist: pandas~=2.2.3
Requires-Dist: pytest~=3.10.1
Requires-Dist: pytest-cov~=2.6.0
Requires-Dist: si-prefix~=1.3.3
Requires-Dist: spacy~=3.0
Requires-Dist: vega~=4.1
Dynamic: author
Dynamic: author-email
Dynamic: description
Dynamic: description-content-type
Dynamic: home-page
Dynamic: license
Dynamic: license-file
Dynamic: requires-dist
Dynamic: summary
